ivenv/__init__.py
ivenv-0.0.1.dist-info/LICENSE
ivenv-0.0.1.dist-info/METADATA
ivenv-0.0.1.dist-info/WHEEL
ivenv-0.0.1.dist-info/top_level.txt
ivenv-0.0.1.dist-info/RECORD
